SteemAX-1.5.4.dist-info/DESCRIPTION.rst
SteemAX-1.5.4.dist-info/METADATA
SteemAX-1.5.4.dist-info/RECORD
SteemAX-1.5.4.dist-info/WHEEL
SteemAX-1.5.4.dist-info/entry_points.txt
SteemAX-1.5.4.dist-info/metadata.json
SteemAX-1.5.4.dist-info/top_level.txt
steemax/__init__.py
steemax/axconfig.py
steemax/axdb.py
steemax/axe.py
steemax/axmsg.py
steemax/axtrans.py
steemax/axverify.py
steemax/db.py
steemax/default.py
steemax/sec.py
steemax/steemax.py
steemax/web.py
