Metadata-Version: 2.0
Name: SteemAX
Version: 1.5.4
Summary: UNKNOWN
Home-page: http://github.com/artolabs/steemax
Author: ArtoLabs
Author-email: artopium@gmail.com
License: MIT
Keywords: steemit steem upvote exchange
Platform: UNKNOWN
Requires-Dist: python-dateutil
Requires-Dist: screenlogger
Requires-Dist: simplesteem
